pylookinremote/__init__.py
pylookinremote/pylookinremote.py
pyLOOKinRemote-2021.11.25.dist-info/LICENSE
pyLOOKinRemote-2021.11.25.dist-info/METADATA
pyLOOKinRemote-2021.11.25.dist-info/WHEEL
pyLOOKinRemote-2021.11.25.dist-info/top_level.txt
pyLOOKinRemote-2021.11.25.dist-info/RECORD
