Metadata-Version: 2.1
Name: pyLOOKinRemote
Version: 2021.11.25
Summary: Unofficial Python module for interacting with LOOKin Remote devices, largely using LOOKin's API.
Home-page: https://github.com/defcello/pyLOOKinRemote
Author: John Crawford
Author-email: jtcrwfrd@gmail.com
License: UNKNOWN
Project-URL: Bug Tracker, https://github.com/defcello/pyLOOKinRemote/issues
Platform: UNKNOWN
Classifier: Programming Language :: Python :: 3
Classifier: License :: OSI Approved :: MIT License
Classifier: Operating System :: OS Independent
Requires-Python: >=3.8
License-File: LICENSE
Requires-Dist: zeroconf
